{"_ts":[1570022915,1570109752],"_r":{"breakdown":{"html":{"bytes":[68868,65383],"requests":[25,22]},"js":{"bytes":[1228553,1218669],"requests":[62,58]},"css":{"bytes":[69371,69371],"requests":[1,1]},"image":{"bytes":[579032,575025],"requests":[63,57]},"flash":{"bytes":[0,0],"requests":[0,0]},"font":{"bytes":[218164,218164],"requests":[7,7]},"video":{"bytes":[6125671,6036116],"requests":[1,1]},"other":{"bytes":[693,184],"requests":[32,29]}},"date":[1570022915,1570109752],"domElements":[2105,2098],"domInteractive":[4606,9942],"firstPaint":[2152.5000000001,7884.7999999998],"fullyLoaded":[20428,25856],"id":["191002_GH_36d02e62f193412492ec9bd1dc5f498c","191003_0F_8c1406b8f1da4d3c85f7bb14dca21c0d"],"loadTime":[13585,20381],"render":[2166,7910],"SpeedIndex":[8664,13882],"TTFB":[926,6339],"videoFrames":[[{"_i":"ms_000000.jpg","_t":0,"_vc":0},{"_i":"ms_002166.jpg","_t":2166,"_vc":17},{"_i":"ms_002220.jpg","_t":2220,"_vc":26},{"_i":"ms_002270.jpg","_t":2270,"_vc":27},{"_i":"ms_002382.jpg","_t":2382,"_vc":27},{"_i":"ms_002424.jpg","_t":2424,"_vc":27},{"_i":"ms_002472.jpg","_t":2472,"_vc":27},{"_i":"ms_002540.jpg","_t":2540,"_vc":27},{"_i":"ms_002773.jpg","_t":2773,"_vc":49},{"_i":"ms_002795.jpg","_t":2795,"_vc":49},{"_i":"ms_003091.jpg","_t":3091,"_vc":52},{"_i":"ms_003158.jpg","_t":3158,"_vc":52},{"_i":"ms_003677.jpg","_t":3677,"_vc":52},{"_i":"ms_004180.jpg","_t":4180,"_vc":52},{"_i":"ms_004682.jpg","_t":4682,"_vc":52},{"_i":"ms_005185.jpg","_t":5185,"_vc":52},{"_i":"ms_005671.jpg","_t":5671,"_vc":52},{"_i":"ms_006174.jpg","_t":6174,"_vc":52},{"_i":"ms_006677.jpg","_t":6677,"_vc":52},{"_i":"ms_007013.jpg","_t":7013,"_vc":52},{"_i":"ms_007595.jpg","_t":7595,"_vc":64},{"_i":"ms_008211.jpg","_t":8211,"_vc":70},{"_i":"ms_008672.jpg","_t":8672,"_vc":70},{"_i":"ms_009158.jpg","_t":9158,"_vc":70},{"_i":"ms_009644.jpg","_t":9644,"_vc":70},{"_i":"ms_010030.jpg","_t":10030,"_vc":70},{"_i":"ms_010667.jpg","_t":10667,"_vc":70},{"_i":"ms_011158.jpg","_t":11158,"_vc":70},{"_i":"ms_011672.jpg","_t":11672,"_vc":70},{"_i":"ms_012174.jpg","_t":12174,"_vc":70},{"_i":"ms_012501.jpg","_t":12501,"_vc":39},{"_i":"ms_013148.jpg","_t":13148,"_vc":68},{"_i":"ms_013682.jpg","_t":13682,"_vc":68},{"_i":"ms_014151.jpg","_t":14151,"_vc":68},{"_i":"ms_014655.jpg","_t":14655,"_vc":68},{"_i":"ms_015157.jpg","_t":15157,"_vc":68},{"_i":"ms_015662.jpg","_t":15662,"_vc":68},{"_i":"ms_016236.jpg","_t":16236,"_vc":68},{"_i":"ms_016532.jpg","_t":16532,"_vc":68},{"_i":"ms_017051.jpg","_t":17051,"_vc":68},{"_i":"ms_017570.jpg","_t":17570,"_vc":68},{"_i":"ms_018007.jpg","_t":18007,"_vc":50},{"_i":"ms_018509.jpg","_t":18509,"_vc":99},{"_i":"ms_019164.jpg","_t":19164,"_vc":99},{"_i":"ms_019665.jpg","_t":19665,"_vc":100},{"_i":"ms_020167.jpg","_t":20167,"_vc":99},{"_i":"ms_020654.jpg","_t":20654,"_vc":100}],[{"_i":"ms_000000.jpg","_t":0,"_vc":0},{"_i":"ms_007910.jpg","_t":7910,"_vc":27},{"_i":"ms_007976.jpg","_t":7976,"_vc":27},{"_i":"ms_008051.jpg","_t":8051,"_vc":52},{"_i":"ms_008103.jpg","_t":8103,"_vc":51},{"_i":"ms_008176.jpg","_t":8176,"_vc":52},{"_i":"ms_008378.jpg","_t":8378,"_vc":52},{"_i":"ms_008580.jpg","_t":8580,"_vc":52},{"_i":"ms_009102.jpg","_t":9102,"_vc":52},{"_i":"ms_009590.jpg","_t":9590,"_vc":52},{"_i":"ms_010094.jpg","_t":10094,"_vc":52},{"_i":"ms_010619.jpg","_t":10619,"_vc":52},{"_i":"ms_011116.jpg","_t":11116,"_vc":52},{"_i":"ms_011597.jpg","_t":11597,"_vc":52},{"_i":"ms_012092.jpg","_t":12092,"_vc":52},{"_i":"ms_012605.jpg","_t":12605,"_vc":52},{"_i":"ms_013100.jpg","_t":13100,"_vc":52},{"_i":"ms_013216.jpg","_t":13216,"_vc":70},{"_i":"ms_013599.jpg","_t":13599,"_vc":70},{"_i":"ms_014102.jpg","_t":14102,"_vc":70},{"_i":"ms_014503.jpg","_t":14503,"_vc":70},{"_i":"ms_015088.jpg","_t":15088,"_vc":70},{"_i":"ms_015571.jpg","_t":15571,"_vc":70},{"_i":"ms_016090.jpg","_t":16090,"_vc":70},{"_i":"ms_016591.jpg","_t":16591,"_vc":70},{"_i":"ms_017091.jpg","_t":17091,"_vc":70},{"_i":"ms_017528.jpg","_t":17528,"_vc":72},{"_i":"ms_018034.jpg","_t":18034,"_vc":70},{"_i":"ms_018578.jpg","_t":18578,"_vc":68},{"_i":"ms_019085.jpg","_t":19085,"_vc":68},{"_i":"ms_019580.jpg","_t":19580,"_vc":68},{"_i":"ms_020082.jpg","_t":20082,"_vc":68},{"_i":"ms_020599.jpg","_t":20599,"_vc":68},{"_i":"ms_021083.jpg","_t":21083,"_vc":68},{"_i":"ms_021585.jpg","_t":21585,"_vc":68},{"_i":"ms_022036.jpg","_t":22036,"_vc":68},{"_i":"ms_022536.jpg","_t":22536,"_vc":68},{"_i":"ms_023005.jpg","_t":23005,"_vc":64},{"_i":"ms_023572.jpg","_t":23572,"_vc":68},{"_i":"ms_024074.jpg","_t":24074,"_vc":100},{"_i":"ms_024574.jpg","_t":24574,"_vc":99},{"_i":"ms_025075.jpg","_t":25075,"_vc":100},{"_i":"ms_025576.jpg","_t":25576,"_vc":99},{"_i":"ms_026079.jpg","_t":26079,"_vc":100}]],"visualComplete":[19665,24074],"lighthouse":[30,30],"pagespeed":[67,67]}}