{"_ts":[1596250268,1596435592,1596623769,1596803079],"_r":{"breakdown":{"html":{"bytes":[107091,59513,106456,38685],"requests":[12,1,11,1]},"js":{"bytes":[943476,0,976812,0],"requests":[22,1,22,1]},"css":{"bytes":[107958,32768,107956,0],"requests":[3,1,3,0]},"image":{"bytes":[258507,0,263047,0],"requests":[24,0,23,0]},"flash":{"bytes":[0,0,0,0],"requests":[0,0,0,0]},"font":{"bytes":[270597,0,270597,0],"requests":[9,0,9,0]},"video":{"bytes":[1705140,0,2719295,0],"requests":[1,0,1,0]},"other":{"bytes":[13136,292124,13170,286551],"requests":[13,15,17,16]}},"date":[1596250268,1596435592,1596623769,1596803079],"domElements":[2810,null,2810,null],"domInteractive":[9934,0,10590,0],"firstPaint":[6266.2,0,6985.400000005,0],"fullyLoaded":[36678,61282,36791,64459],"id":["200801_Q1_864646f69679f73a18db5db4f13fe56c","200803_HQ_380a64035f22b3fd24bd061b47d95e1d","200805_3D_448b02093aeb6406782a0666c89e7a70","200807_A5_6121999eba06f16a974c011404d610ee"],"loadTime":[25105,61282,22499,64459],"render":[6273,0,6982,0],"SpeedIndex":[10456,0,11120,0],"TTFB":[3730,2879,4164,4171],"videoFrames":[[{"_i":"ms_000000.jpg","_t":0,"_vc":0},{"_i":"ms_006273.jpg","_t":6273,"_vc":63},{"_i":"ms_006323.jpg","_t":6323,"_vc":63},{"_i":"ms_006361.jpg","_t":6361,"_vc":63},{"_i":"ms_006416.jpg","_t":6416,"_vc":63},{"_i":"ms_006480.jpg","_t":6480,"_vc":63},{"_i":"ms_006560.jpg","_t":6560,"_vc":63},{"_i":"ms_006613.jpg","_t":6613,"_vc":63},{"_i":"ms_006756.jpg","_t":6756,"_vc":63},{"_i":"ms_008899.jpg","_t":8899,"_vc":63},{"_i":"ms_008921.jpg","_t":8921,"_vc":63},{"_i":"ms_014298.jpg","_t":14298,"_vc":71},{"_i":"ms_014586.jpg","_t":14586,"_vc":71},{"_i":"ms_018484.jpg","_t":18484,"_vc":100}],[{"_i":"ms_000000.jpg","_t":0,"_vc":100}],[{"_i":"ms_000000.jpg","_t":0,"_vc":0},{"_i":"ms_006982.jpg","_t":6982,"_vc":63},{"_i":"ms_007028.jpg","_t":7028,"_vc":63},{"_i":"ms_007052.jpg","_t":7052,"_vc":63},{"_i":"ms_007103.jpg","_t":7103,"_vc":63},{"_i":"ms_007137.jpg","_t":7137,"_vc":63},{"_i":"ms_007190.jpg","_t":7190,"_vc":63},{"_i":"ms_007251.jpg","_t":7251,"_vc":63},{"_i":"ms_007304.jpg","_t":7304,"_vc":63},{"_i":"ms_008114.jpg","_t":8114,"_vc":63},{"_i":"ms_010138.jpg","_t":10138,"_vc":63},{"_i":"ms_010994.jpg","_t":10994,"_vc":63},{"_i":"ms_015030.jpg","_t":15030,"_vc":71},{"_i":"ms_015312.jpg","_t":15312,"_vc":71},{"_i":"ms_016752.jpg","_t":16752,"_vc":71},{"_i":"ms_019031.jpg","_t":19031,"_vc":100}],[{"_i":"ms_000000.jpg","_t":0,"_vc":100}]],"visualComplete":[18484,0,19031,0],"lighthouse":[28,null,28,null],"pagespeed":[null,null,null,null]}}