{"_ts":[1525399252,1525457511,1525485496,1525529398],"_r":{"breakdown":{"html":{"bytes":[57081,59708,59340,59719],"requests":[32,36,35,36]},"js":{"bytes":[800978,822005,821374,818725],"requests":[64,65,65,66]},"css":{"bytes":[95016,95048,95026,95034],"requests":[1,1,1,1]},"image":{"bytes":[2015637,2021716,2021029,2075000],"requests":[61,71,70,71]},"flash":{"bytes":[0,0,0,0],"requests":[0,0,0,0]},"font":{"bytes":[288305,288357,288314,288324],"requests":[8,8,8,8]},"video":{"bytes":[4604944,4586591,4422054,4766103],"requests":[10,9,7,6]},"other":{"bytes":[26554,26779,27189,26780],"requests":[22,37,41,36]}},"date":[1525399252,1525457511,1525485496,1525529398],"domElements":[1717,1732,1732,1732],"domInteractive":[1919,6780,1835,7693],"firstPaint":[1912.6000000033,6743.199999999,1799.9000000054,6783.6000000001],"fullyLoaded":[23269,28180,23995,37293],"id":["180504_89_b65d96d0dbc08d650b6526a52f8fe740","180504_3K_9e8d8c781ab8573a122d7a322460f1db","180505_FA_c2a8c1c0ec81870913c02668a76c226b","180505_K0_09a19c112d0ca47a81c8d55b651147e6"],"loadTime":[18814,23833,20998,34312],"render":[1900,6800,1800,6900],"SpeedIndex":[11024,16100,10574,20573],"TTFB":[1441,6275,1318,6069],"videoFrames":[[{"_i":"ms_000000.jpg","_t":0,"_vc":0},{"_i":"ms_001900.jpg","_t":1900,"_vc":19},{"_i":"ms_002000.jpg","_t":2000,"_vc":19},{"_i":"ms_002100.jpg","_t":2100,"_vc":28},{"_i":"ms_002400.jpg","_t":2400,"_vc":28},{"_i":"ms_002500.jpg","_t":2500,"_vc":68},{"_i":"ms_002900.jpg","_t":2900,"_vc":68},{"_i":"ms_003400.jpg","_t":3400,"_vc":68},{"_i":"ms_003500.jpg","_t":3500,"_vc":68},{"_i":"ms_003600.jpg","_t":3600,"_vc":68},{"_i":"ms_003700.jpg","_t":3700,"_vc":68},{"_i":"ms_003900.jpg","_t":3900,"_vc":68},{"_i":"ms_004400.jpg","_t":4400,"_vc":68},{"_i":"ms_004500.jpg","_t":4500,"_vc":68},{"_i":"ms_004900.jpg","_t":4900,"_vc":68},{"_i":"ms_005400.jpg","_t":5400,"_vc":68},{"_i":"ms_005900.jpg","_t":5900,"_vc":68},{"_i":"ms_006400.jpg","_t":6400,"_vc":68},{"_i":"ms_006900.jpg","_t":6900,"_vc":68},{"_i":"ms_007400.jpg","_t":7400,"_vc":68},{"_i":"ms_007600.jpg","_t":7600,"_vc":68},{"_i":"ms_008000.jpg","_t":8000,"_vc":68},{"_i":"ms_008800.jpg","_t":8800,"_vc":68},{"_i":"ms_009200.jpg","_t":9200,"_vc":68},{"_i":"ms_009500.jpg","_t":9500,"_vc":68},{"_i":"ms_010100.jpg","_t":10100,"_vc":68},{"_i":"ms_010500.jpg","_t":10500,"_vc":68},{"_i":"ms_011000.jpg","_t":11000,"_vc":26},{"_i":"ms_011500.jpg","_t":11500,"_vc":70},{"_i":"ms_012300.jpg","_t":12300,"_vc":52},{"_i":"ms_013400.jpg","_t":13400,"_vc":52},{"_i":"ms_014400.jpg","_t":14400,"_vc":52},{"_i":"ms_015000.jpg","_t":15000,"_vc":52},{"_i":"ms_016000.jpg","_t":16000,"_vc":52},{"_i":"ms_017000.jpg","_t":17000,"_vc":51},{"_i":"ms_018400.jpg","_t":18400,"_vc":70},{"_i":"ms_019000.jpg","_t":19000,"_vc":70},{"_i":"ms_020000.jpg","_t":20000,"_vc":70},{"_i":"ms_021000.jpg","_t":21000,"_vc":70},{"_i":"ms_022000.jpg","_t":22000,"_vc":70},{"_i":"ms_023000.jpg","_t":23000,"_vc":27},{"_i":"ms_024400.jpg","_t":24400,"_vc":100},{"_i":"ms_025400.jpg","_t":25400,"_vc":100}],[{"_i":"ms_000000.jpg","_t":0,"_vc":0},{"_i":"ms_006800.jpg","_t":6800,"_vc":19},{"_i":"ms_007000.jpg","_t":7000,"_vc":38},{"_i":"ms_007100.jpg","_t":7100,"_vc":38},{"_i":"ms_007200.jpg","_t":7200,"_vc":38},{"_i":"ms_007300.jpg","_t":7300,"_vc":38},{"_i":"ms_007500.jpg","_t":7500,"_vc":68},{"_i":"ms_007800.jpg","_t":7800,"_vc":68},{"_i":"ms_008300.jpg","_t":8300,"_vc":68},{"_i":"ms_008500.jpg","_t":8500,"_vc":68},{"_i":"ms_008600.jpg","_t":8600,"_vc":68},{"_i":"ms_008800.jpg","_t":8800,"_vc":68},{"_i":"ms_009200.jpg","_t":9200,"_vc":68},{"_i":"ms_009300.jpg","_t":9300,"_vc":68},{"_i":"ms_009600.jpg","_t":9600,"_vc":68},{"_i":"ms_009800.jpg","_t":9800,"_vc":68},{"_i":"ms_010300.jpg","_t":10300,"_vc":68},{"_i":"ms_010800.jpg","_t":10800,"_vc":68},{"_i":"ms_011300.jpg","_t":11300,"_vc":68},{"_i":"ms_011800.jpg","_t":11800,"_vc":68},{"_i":"ms_012300.jpg","_t":12300,"_vc":68},{"_i":"ms_012800.jpg","_t":12800,"_vc":68},{"_i":"ms_013300.jpg","_t":13300,"_vc":68},{"_i":"ms_013800.jpg","_t":13800,"_vc":68},{"_i":"ms_014200.jpg","_t":14200,"_vc":68},{"_i":"ms_014500.jpg","_t":14500,"_vc":68},{"_i":"ms_015100.jpg","_t":15100,"_vc":68},{"_i":"ms_015500.jpg","_t":15500,"_vc":68},{"_i":"ms_016000.jpg","_t":16000,"_vc":19},{"_i":"ms_016500.jpg","_t":16500,"_vc":70},{"_i":"ms_017100.jpg","_t":17100,"_vc":52},{"_i":"ms_018300.jpg","_t":18300,"_vc":52},{"_i":"ms_019000.jpg","_t":19000,"_vc":52},{"_i":"ms_020000.jpg","_t":20000,"_vc":52},{"_i":"ms_021000.jpg","_t":21000,"_vc":52},{"_i":"ms_022300.jpg","_t":22300,"_vc":51},{"_i":"ms_023300.jpg","_t":23300,"_vc":51},{"_i":"ms_024100.jpg","_t":24100,"_vc":70},{"_i":"ms_025000.jpg","_t":25000,"_vc":70},{"_i":"ms_026000.jpg","_t":26000,"_vc":70},{"_i":"ms_027000.jpg","_t":27000,"_vc":70},{"_i":"ms_028000.jpg","_t":28000,"_vc":25},{"_i":"ms_029300.jpg","_t":29300,"_vc":100},{"_i":"ms_029800.jpg","_t":29800,"_vc":100}],[{"_i":"ms_000000.jpg","_t":0,"_vc":0},{"_i":"ms_001800.jpg","_t":1800,"_vc":19},{"_i":"ms_001900.jpg","_t":1900,"_vc":19},{"_i":"ms_002000.jpg","_t":2000,"_vc":20},{"_i":"ms_002300.jpg","_t":2300,"_vc":20},{"_i":"ms_002400.jpg","_t":2400,"_vc":68},{"_i":"ms_002800.jpg","_t":2800,"_vc":68},{"_i":"ms_003300.jpg","_t":3300,"_vc":68},{"_i":"ms_003500.jpg","_t":3500,"_vc":68},{"_i":"ms_003800.jpg","_t":3800,"_vc":68},{"_i":"ms_004200.jpg","_t":4200,"_vc":68},{"_i":"ms_004300.jpg","_t":4300,"_vc":68},{"_i":"ms_004500.jpg","_t":4500,"_vc":68},{"_i":"ms_004800.jpg","_t":4800,"_vc":68},{"_i":"ms_005300.jpg","_t":5300,"_vc":68},{"_i":"ms_005800.jpg","_t":5800,"_vc":68},{"_i":"ms_006300.jpg","_t":6300,"_vc":68},{"_i":"ms_006800.jpg","_t":6800,"_vc":68},{"_i":"ms_007300.jpg","_t":7300,"_vc":68},{"_i":"ms_007600.jpg","_t":7600,"_vc":68},{"_i":"ms_008300.jpg","_t":8300,"_vc":68},{"_i":"ms_008800.jpg","_t":8800,"_vc":68},{"_i":"ms_009300.jpg","_t":9300,"_vc":68},{"_i":"ms_009500.jpg","_t":9500,"_vc":68},{"_i":"ms_010000.jpg","_t":10000,"_vc":68},{"_i":"ms_010500.jpg","_t":10500,"_vc":68},{"_i":"ms_011000.jpg","_t":11000,"_vc":46},{"_i":"ms_011500.jpg","_t":11500,"_vc":69},{"_i":"ms_012300.jpg","_t":12300,"_vc":70},{"_i":"ms_012500.jpg","_t":12500,"_vc":51},{"_i":"ms_013300.jpg","_t":13300,"_vc":51},{"_i":"ms_014300.jpg","_t":14300,"_vc":52},{"_i":"ms_015200.jpg","_t":15200,"_vc":52},{"_i":"ms_016100.jpg","_t":16100,"_vc":52},{"_i":"ms_017000.jpg","_t":17000,"_vc":52},{"_i":"ms_018300.jpg","_t":18300,"_vc":52},{"_i":"ms_019300.jpg","_t":19300,"_vc":52},{"_i":"ms_020300.jpg","_t":20300,"_vc":70},{"_i":"ms_021000.jpg","_t":21000,"_vc":70},{"_i":"ms_022000.jpg","_t":22000,"_vc":70},{"_i":"ms_023000.jpg","_t":23000,"_vc":70},{"_i":"ms_024300.jpg","_t":24300,"_vc":100},{"_i":"ms_025300.jpg","_t":25300,"_vc":100},{"_i":"ms_025800.jpg","_t":25800,"_vc":100}],[{"_i":"ms_000000.jpg","_t":0,"_vc":0},{"_i":"ms_006900.jpg","_t":6900,"_vc":18},{"_i":"ms_007100.jpg","_t":7100,"_vc":18},{"_i":"ms_007200.jpg","_t":7200,"_vc":17},{"_i":"ms_007600.jpg","_t":7600,"_vc":19},{"_i":"ms_007700.jpg","_t":7700,"_vc":18},{"_i":"ms_007800.jpg","_t":7800,"_vc":18},{"_i":"ms_008000.jpg","_t":8000,"_vc":58},{"_i":"ms_008100.jpg","_t":8100,"_vc":58},{"_i":"ms_008300.jpg","_t":8300,"_vc":59},{"_i":"ms_008400.jpg","_t":8400,"_vc":59},{"_i":"ms_008600.jpg","_t":8600,"_vc":59},{"_i":"ms_009100.jpg","_t":9100,"_vc":59},{"_i":"ms_009600.jpg","_t":9600,"_vc":59},{"_i":"ms_010100.jpg","_t":10100,"_vc":59},{"_i":"ms_010600.jpg","_t":10600,"_vc":59},{"_i":"ms_011100.jpg","_t":11100,"_vc":59},{"_i":"ms_011600.jpg","_t":11600,"_vc":59},{"_i":"ms_012100.jpg","_t":12100,"_vc":59},{"_i":"ms_012600.jpg","_t":12600,"_vc":59},{"_i":"ms_013100.jpg","_t":13100,"_vc":59},{"_i":"ms_013600.jpg","_t":13600,"_vc":59},{"_i":"ms_014100.jpg","_t":14100,"_vc":59},{"_i":"ms_014600.jpg","_t":14600,"_vc":59},{"_i":"ms_015100.jpg","_t":15100,"_vc":59},{"_i":"ms_015600.jpg","_t":15600,"_vc":59},{"_i":"ms_016000.jpg","_t":16000,"_vc":59},{"_i":"ms_016500.jpg","_t":16500,"_vc":59},{"_i":"ms_017000.jpg","_t":17000,"_vc":59},{"_i":"ms_017500.jpg","_t":17500,"_vc":59},{"_i":"ms_018000.jpg","_t":18000,"_vc":29},{"_i":"ms_019100.jpg","_t":19100,"_vc":56},{"_i":"ms_020100.jpg","_t":20100,"_vc":56},{"_i":"ms_021100.jpg","_t":21100,"_vc":56},{"_i":"ms_022000.jpg","_t":22000,"_vc":56},{"_i":"ms_023000.jpg","_t":23000,"_vc":56},{"_i":"ms_024100.jpg","_t":24100,"_vc":56},{"_i":"ms_025000.jpg","_t":25000,"_vc":56},{"_i":"ms_026100.jpg","_t":26100,"_vc":69},{"_i":"ms_027100.jpg","_t":27100,"_vc":69},{"_i":"ms_028000.jpg","_t":28000,"_vc":69},{"_i":"ms_029000.jpg","_t":29000,"_vc":69},{"_i":"ms_030000.jpg","_t":30000,"_vc":29},{"_i":"ms_031100.jpg","_t":31100,"_vc":57},{"_i":"ms_032100.jpg","_t":32100,"_vc":57},{"_i":"ms_033100.jpg","_t":33100,"_vc":57},{"_i":"ms_034000.jpg","_t":34000,"_vc":57},{"_i":"ms_035000.jpg","_t":35000,"_vc":57},{"_i":"ms_036100.jpg","_t":36100,"_vc":56},{"_i":"ms_037000.jpg","_t":37000,"_vc":33},{"_i":"ms_037400.jpg","_t":37400,"_vc":100}]],"visualComplete":[24400,29300,24300,37400],"lighthouse":[54,54,63,54],"pagespeed":[59,59,58,58]}}