{"_ts":[1533109486],"_r":{"breakdown":{"html":{"bytes":[70078],"requests":[24]},"js":{"bytes":[843857],"requests":[65]},"css":{"bytes":[73601],"requests":[1]},"image":{"bytes":[1423951],"requests":[67]},"flash":{"bytes":[0],"requests":[0]},"font":{"bytes":[288801],"requests":[8]},"video":{"bytes":[0],"requests":[0]},"other":{"bytes":[19316],"requests":[25]}},"date":[1533109486],"domElements":[1800],"domInteractive":[3081],"firstPaint":[695.4000000005],"fullyLoaded":[9889],"id":["180801_QZ_7d3e6c42480d463cc3e30d502e89310d"],"loadTime":[8500],"render":[700],"SpeedIndex":[4061],"TTFB":[267],"videoFrames":[[{"_i":"ms_000000.jpg","_t":0,"_vc":0},{"_i":"ms_000700.jpg","_t":700,"_vc":32},{"_i":"ms_000900.jpg","_t":900,"_vc":38},{"_i":"ms_001000.jpg","_t":1000,"_vc":38},{"_i":"ms_001100.jpg","_t":1100,"_vc":40},{"_i":"ms_001200.jpg","_t":1200,"_vc":40},{"_i":"ms_001600.jpg","_t":1600,"_vc":40},{"_i":"ms_001700.jpg","_t":1700,"_vc":40},{"_i":"ms_001900.jpg","_t":1900,"_vc":40},{"_i":"ms_002000.jpg","_t":2000,"_vc":40},{"_i":"ms_002200.jpg","_t":2200,"_vc":40},{"_i":"ms_002600.jpg","_t":2600,"_vc":40},{"_i":"ms_002700.jpg","_t":2700,"_vc":40},{"_i":"ms_003200.jpg","_t":3200,"_vc":40},{"_i":"ms_003700.jpg","_t":3700,"_vc":40},{"_i":"ms_004300.jpg","_t":4300,"_vc":41},{"_i":"ms_004500.jpg","_t":4500,"_vc":76},{"_i":"ms_004600.jpg","_t":4600,"_vc":76},{"_i":"ms_004700.jpg","_t":4700,"_vc":76},{"_i":"ms_004800.jpg","_t":4800,"_vc":76},{"_i":"ms_004900.jpg","_t":4900,"_vc":76},{"_i":"ms_005000.jpg","_t":5000,"_vc":77},{"_i":"ms_005100.jpg","_t":5100,"_vc":77},{"_i":"ms_005200.jpg","_t":5200,"_vc":78},{"_i":"ms_005300.jpg","_t":5300,"_vc":77},{"_i":"ms_005400.jpg","_t":5400,"_vc":77},{"_i":"ms_005500.jpg","_t":5500,"_vc":78},{"_i":"ms_005600.jpg","_t":5600,"_vc":78},{"_i":"ms_005800.jpg","_t":5800,"_vc":78},{"_i":"ms_006000.jpg","_t":6000,"_vc":77},{"_i":"ms_006100.jpg","_t":6100,"_vc":77},{"_i":"ms_006200.jpg","_t":6200,"_vc":77},{"_i":"ms_007300.jpg","_t":7300,"_vc":78},{"_i":"ms_007500.jpg","_t":7500,"_vc":78},{"_i":"ms_007800.jpg","_t":7800,"_vc":78},{"_i":"ms_008500.jpg","_t":8500,"_vc":78},{"_i":"ms_008800.jpg","_t":8800,"_vc":92},{"_i":"ms_008900.jpg","_t":8900,"_vc":75},{"_i":"ms_009000.jpg","_t":9000,"_vc":68},{"_i":"ms_009100.jpg","_t":9100,"_vc":75},{"_i":"ms_009200.jpg","_t":9200,"_vc":100}]],"visualComplete":[9200],"lighthouse":[35],"pagespeed":[59]}}