{"_ts":[1567298211],"_r":{"breakdown":{"html":{"bytes":[16494],"requests":[20]},"js":{"bytes":[620901],"requests":[34]},"css":{"bytes":[18988],"requests":[3]},"image":{"bytes":[4023583],"requests":[35]},"flash":{"bytes":[0],"requests":[0]},"font":{"bytes":[936576],"requests":[11]},"video":{"bytes":[0],"requests":[0]},"other":{"bytes":[1409],"requests":[13]}},"date":[1567298211],"domElements":[901],"domInteractive":[5586],"firstPaint":[3716.0250000015],"fullyLoaded":[13905],"id":["190901_22_448a8448bab30a75821b49eae81971c5"],"loadTime":[13315],"render":[3700],"SpeedIndex":[6333],"TTFB":[2372],"videoFrames":[[{"_i":"ms_000000.jpg","_t":0,"_vc":0},{"_i":"ms_003700.jpg","_t":3700,"_vc":43},{"_i":"ms_003800.jpg","_t":3800,"_vc":43},{"_i":"ms_003900.jpg","_t":3900,"_vc":43},{"_i":"ms_004000.jpg","_t":4000,"_vc":56},{"_i":"ms_004700.jpg","_t":4700,"_vc":56},{"_i":"ms_005100.jpg","_t":5100,"_vc":73},{"_i":"ms_006200.jpg","_t":6200,"_vc":62},{"_i":"ms_006800.jpg","_t":6800,"_vc":69},{"_i":"ms_007000.jpg","_t":7000,"_vc":69},{"_i":"ms_007600.jpg","_t":7600,"_vc":69},{"_i":"ms_007800.jpg","_t":7800,"_vc":69},{"_i":"ms_008500.jpg","_t":8500,"_vc":69},{"_i":"ms_009200.jpg","_t":9200,"_vc":69},{"_i":"ms_011100.jpg","_t":11100,"_vc":69},{"_i":"ms_011200.jpg","_t":11200,"_vc":69},{"_i":"ms_011300.jpg","_t":11300,"_vc":74},{"_i":"ms_011400.jpg","_t":11400,"_vc":81},{"_i":"ms_011500.jpg","_t":11500,"_vc":90},{"_i":"ms_011600.jpg","_t":11600,"_vc":97},{"_i":"ms_011700.jpg","_t":11700,"_vc":100}]],"visualComplete":[11700],"lighthouse":[19],"pagespeed":[42]}}